{
  "resource_uri": "https://www.courtlistener.com/api/rest/v3/opinions/101388/",
  "id": 101388,
  "absolute_url": "/opinion/101388/t-tomich-harry-f-scott-and-h-mulberger-v-union-trust-co-spokane/",
  "cluster": "https://www.courtlistener.com/api/rest/v3/clusters/101388/",
  "author": null,
  "joined_by": [],
  "author_str": "",
  "per_curiam": false,
  "joined_by_str": "",
  "date_created": "2010-04-28T16:48:46Z",
  "date_modified": "2020-02-21T21:20:29.902247Z",
  "type": "010combined",
  "sha1": "f3986bd8838f58c870c7ebe981eb6486fa9e0a1d",
  "page_count": null,
  "download_url": "http://bulk.resource.org/courts.gov/c/US/278/278.US.664.14.html",
  "local_path": null,
  "plain_text": "",
  "html": "<p class=\"case_cite\">278 U.S. 664</p>\n    <p class=\"case_cite\">49 S.Ct. 340</p>\n    <p class=\"case_cite\">73 L.Ed. 570</p>\n    <p class=\"parties\">T. TOMICH, Harry F. Scott, and H. Mulberger, appellants,<br>v.<br>UNION TRUST CO., Spokane &amp; Eastern Trust Company.<a class=\"footnote\" href=\"#fn1\" id=\"fn1_ref\">1</a></p>\n    <p class=\"docket\">No. 14.</p>\n    <p class=\"court\">Supreme Court of the United States</p>\n    <p class=\"date\">January 2, 1929</p>\n    <div class=\"num\" id=\"p1\">\n      <span class=\"num\">1</span>\n      <p class=\"indent\">Mr. John A. Shelton, of Butte, Mont., for appellants.</p>\n    </div>\n    <div class=\"num\" id=\"p2\">\n      <span class=\"num\">2</span>\n      <p class=\"indent\">Dismissed with costs pursuant to paragraph 2 of rule 13.</p>\n    </div>\n    <div class=\"footnotes\">\n      <div class=\"footnote\" id=\"fn1\">\n        <a class=\"footnote\" href=\"#fn1_ref\">1</a>\n        <p> Transcript in this case was withdrawn from Supreme Court and filed in Circuit Court of Appeals. For opinion in that court, see 31 F.(2d) 515.</p>\n      </div>\n    </div>\n    ",
  "html_lawbox": "",
  "html_columbia": "",
  "xml_harvard": "",
  "html_with_citations": "<p class=\"case_cite\"><span class=\"citation no-link\"><span class=\"volume\">278</span> <span class=\"reporter\">U.S.</span> <span class=\"page\">664</span></span></p>\n    <p class=\"case_cite\"><span class=\"citation no-link\"><span class=\"volume\">49</span> <span class=\"reporter\">S. Ct.</span> <span class=\"page\">340</span></span></p>\n    <p class=\"case_cite\"><span class=\"citation no-link\"><span class=\"volume\">73</span> <span class=\"reporter\">L. Ed.</span> <span class=\"page\">570</span></span></p>\n    <p class=\"parties\">T. TOMICH, Harry F. Scott, and H. Mulberger, appellants,<br>v.<br>UNION TRUST CO., Spokane &amp; Eastern Trust Company.<a class=\"footnote\" href=\"#fn1\" id=\"fn1_ref\">1</a></p>\n    <p class=\"docket\">No. 14.</p>\n    <p class=\"court\">Supreme Court of the United States</p>\n    <p class=\"date\">January 2, 1929</p>\n    <div class=\"num\" id=\"p1\">\n      <span class=\"num\">1</span>\n      <p class=\"indent\">Mr. John A. Shelton, of Butte, Mont., for appellants.</p>\n    </div>\n    <div class=\"num\" id=\"p2\">\n      <span class=\"num\">2</span>\n      <p class=\"indent\">Dismissed with costs pursuant to paragraph 2 of rule 13.</p>\n    </div>\n    <div class=\"footnotes\">\n      <div class=\"footnote\" id=\"fn1\">\n        <a class=\"footnote\" href=\"#fn1_ref\">1</a>\n        <p> Transcript in this case was withdrawn from Supreme Court and filed in Circuit Court of Appeals. For opinion in that court, see 31 F.(2d) 515.</p>\n      </div>\n    </div>\n    ",
  "extracted_by_ocr": false,
  "opinions_cited": []
}